[{"id":"dek_1773254096444_6","tur":"alacak","tutar":230.1,"tarih":"2022-08-18","saat":"","aciklama":"DÜZ BAĞLANTI 20*130 [BA20130] 100 ADET","no":"0018801","belge_no":""},{"id":"dek_1773254096444_7","tur":"alacak","tutar":106.2,"tarih":"2022-08-18","saat":"","aciklama":"KORNİŞ DEMİRİ [BA620] 50 ADET","no":"0018802","belge_no":""},{"id":"dek_1773254096444_8","tur":"odeme","tutar":350,"tarih":"2022-08-26","saat":"","aciklama":"ÖDENEN PARA","no":"0018958","belge_no":""},{"id":"dek_1773254096444_9","tur":"alacak","tutar":521.09,"tarih":"2022-09-08","saat":"","aciklama":"ALINAN MALZEME","no":"0019304","belge_no":""},{"id":"dek_1773254096444_10","tur":"odeme","tutar":500,"tarih":"2022-09-09","saat":"","aciklama":"ÖDENEN PARA","no":"0019305","belge_no":""},{"id":"dek_1773254096444_11","tur":"alacak","tutar":573.48,"tarih":"2022-09-13","saat":"","aciklama":"TYSON ŞERİT METRE 5*25 MM 12 ADET","no":"0019449","belge_no":""},{"id":"dek_1773254096444_12","tur":"odeme","tutar":500,"tarih":"2022-09-16","saat":"","aciklama":"ÖDENEN PARA","no":"0019450","belge_no":""},{"id":"dek_1773254096444_13","tur":"alacak","tutar":4850.33,"tarih":"2022-10-08","saat":"","aciklama":"ALINAN MALZEME","no":"0020214","belge_no":""},{"id":"dek_1773254096444_14","tur":"odeme","tutar":1000,"tarih":"2022-10-14","saat":"","aciklama":"ÖDENEN PARA","no":"0020215","belge_no":""},{"id":"dek_1773254096444_15","tur":"odeme","tutar":159.3,"tarih":"2022-10-21","saat":"","aciklama":"İADE FATURASI","no":"0020429","belge_no":""},{"id":"dek_1773254096444_16","tur":"odeme","tutar":700,"tarih":"2022-10-21","saat":"","aciklama":"ÖDENEN PARA","no":"0020449","belge_no":""},{"id":"dek_1773254096444_17","tur":"odeme","tutar":1000,"tarih":"2022-10-28","saat":"","aciklama":"ÖDENEN PARA","no":"0020623","belge_no":""},{"id":"dek_1773254096444_18","tur":"odeme","tutar":500,"tarih":"2022-11-04","saat":"","aciklama":"ÖDENEN PARA","no":"0020758","belge_no":""},{"id":"dek_1773254096444_19","tur":"odeme","tutar":500,"tarih":"2022-11-11","saat":"","aciklama":"ÖDENEN PARA","no":"0020965","belge_no":""},{"id":"dek_1773254096444_20","tur":"odeme","tutar":500,"tarih":"2022-11-18","saat":"","aciklama":"ÖDENEN PARA","no":"0021151","belge_no":""},{"id":"dek_1773254096444_21","tur":"odeme","tutar":500,"tarih":"2022-12-09","saat":"","aciklama":"ÖDENEN PARA","no":"0021632","belge_no":""},{"id":"dek_1773254096444_22","tur":"alacak","tutar":6741.85,"tarih":"2023-01-05","saat":"","aciklama":"ALINAN MALZEME","no":"0022225","belge_no":""},{"id":"dek_1773254096444_23","tur":"odeme","tutar":1000,"tarih":"2023-01-13","saat":"","aciklama":"ÖDENEN PARA","no":"0022351","belge_no":""},{"id":"dek_1773254096444_24","tur":"odeme","tutar":1000,"tarih":"2023-01-20","saat":"","aciklama":"ÖDENEN PARA","no":"0022479","belge_no":""},{"id":"dek_1773254096444_25","tur":"odeme","tutar":1000,"tarih":"2023-01-27","saat":"","aciklama":"ÖDENEN PARA","no":"0022615","belge_no":""},{"id":"dek_1773254096444_26","tur":"alacak","tutar":1979.89,"tarih":"2023-02-03","saat":"","aciklama":"ALINAN MALZEME","no":"0022784","belge_no":""},{"id":"dek_1773254096444_27","tur":"odeme","tutar":1000,"tarih":"2023-02-03","saat":"","aciklama":"ÖDENEN PARA","no":"0022785","belge_no":""},{"id":"dek_1773254096444_28","tur":"odeme","tutar":1000,"tarih":"2023-02-10","saat":"","aciklama":"ÖDENEN PARA","no":"0022912","belge_no":""},{"id":"dek_1773254096444_29","tur":"alacak","tutar":2294.81,"tarih":"2023-02-11","saat":"","aciklama":"ALINAN MALZEME","no":"0023000","belge_no":""},{"id":"dek_1773254096444_30","tur":"alacak","tutar":1017.46,"tarih":"2023-02-18","saat":"","aciklama":"ALINAN MALZEME","no":"0023095","belge_no":""},{"id":"dek_1773254096444_31","tur":"odeme","tutar":1000,"tarih":"2023-02-24","saat":"","aciklama":"ÖDENEN PARA","no":"0023227","belge_no":""},{"id":"dek_1773254096444_32","tur":"odeme","tutar":10000,"tarih":"2023-03-03","saat":"","aciklama":"WOLD BUSINESS KART İLE ÖDEDİM 6 TAKSİT","no":"0023487","belge_no":""},{"id":"dek_1773254096444_33","tur":"alacak","tutar":4701.5,"tarih":"2023-03-23","saat":"","aciklama":"ALINAN MALZEME","no":"0024097","belge_no":""},{"id":"dek_1773254096444_34","tur":"alacak","tutar":14132.06,"tarih":"2023-04-13","saat":"","aciklama":"ALINAN MALZEME","no":"0024727","belge_no":""},{"id":"dek_1773254096444_35","tur":"odeme","tutar":1000,"tarih":"2023-04-14","saat":"","aciklama":"ÖDENEN PARA","no":"0024810","belge_no":""},{"id":"dek_1773254096444_36","tur":"odeme","tutar":1000,"tarih":"2023-04-29","saat":"","aciklama":"ÖDENEN PARA","no":"0025217","belge_no":""},{"id":"dek_1773254096444_37","tur":"alacak","tutar":778.8,"tarih":"2023-05-01","saat":"","aciklama":"ALINAN MALZEME","no":"0025365","belge_no":""},{"id":"dek_1773254096444_38","tur":"odeme","tutar":1000,"tarih":"2023-05-12","saat":"","aciklama":"ÖDENEN PARA","no":"0025619","belge_no":""},{"id":"dek_1773254096444_39","tur":"odeme","tutar":1000,"tarih":"2023-05-19","saat":"","aciklama":"ÖDENEN PARA","no":"0025814","belge_no":""},{"id":"dek_1773254096444_40","tur":"odeme","tutar":1000,"tarih":"2023-06-02","saat":"","aciklama":"ÖDENEN PARA","no":"0026267","belge_no":""},{"id":"dek_1773254096444_41","tur":"odeme","tutar":1000,"tarih":"2023-06-09","saat":"","aciklama":"ÖDENEN PARA","no":"0026449","belge_no":""},{"id":"dek_1773254096444_42","tur":"odeme","tutar":8500,"tarih":"2023-06-16","saat":"","aciklama":"MAXMUM KREDİ KARTI İLE ÖDEDİM 10 TAKSİT","no":"0026677","belge_no":""},{"id":"dek_1773254096444_43","tur":"alacak","tutar":1100,"tarih":"2023-06-17","saat":"","aciklama":"PRONTO UZUN MUSLUK AÇ-KAPA 20 ADET 55,00 TL DEN","no":"0027064","belge_no":""},{"id":"dek_1773254096444_44","tur":"alacak","tutar":1100,"tarih":"2023-06-17","saat":"","aciklama":"PRONTO KISA MUSLUK AÇ-KAPA 20 ADET 55,00 TL DEN","no":"0027065","belge_no":""},{"id":"dek_1773254096444_45","tur":"alacak","tutar":1100,"tarih":"2023-06-17","saat":"","aciklama":"PRONTO ÇAM MUSLUĞU AÇ-KAPA 20 ADET 55,00 TL DEN","no":"0027066","belge_no":""},{"id":"dek_1773254096444_46","tur":"alacak","tutar":520,"tarih":"2023-06-17","saat":"","aciklama":"PRONTO UZUN MUSLUK ÇEVİRMELİ 10 ADET 52,00 TL DEN","no":"0027067","belge_no":""},{"id":"dek_1773254096444_47","tur":"alacak","tutar":520,"tarih":"2023-06-17","saat":"","aciklama":"PRONTO KISA MUSLUK ÇEVİRMELİ 10 ADET 52,00 TL DEN","no":"0027068","belge_no":""},{"id":"dek_1773254096444_48","tur":"alacak","tutar":520,"tarih":"2023-06-17","saat":"","aciklama":"PRONTO ÇAM MUSLUĞU ÇEVİRMELİ 10 ADET 52,00 TL DEN","no":"0027069","belge_no":""},{"id":"dek_1773254096444_49","tur":"odeme","tutar":4000,"tarih":"2023-07-08","saat":"","aciklama":"ÖDENEN PARA","no":"0027297","belge_no":""},{"id":"dek_1773254096444_50","tur":"odeme","tutar":800,"tarih":"2023-07-14","saat":"","aciklama":"ÖDENEN PARA","no":"0027495","belge_no":""},{"id":"dek_1773254096444_51","tur":"alacak","tutar":1906.56,"tarih":"2023-07-21","saat":"","aciklama":"ALINAN MALZEME","no":"0027710","belge_no":""},{"id":"dek_1773254096444_52","tur":"odeme","tutar":60,"tarih":"2023-07-21","saat":"","aciklama":"ÖDENEN PARA","no":"0027711","belge_no":""},{"id":"dek_1773254096444_53","tur":"odeme","tutar":500,"tarih":"2023-07-28","saat":"","aciklama":"ÖDENEN PARA","no":"0027908","belge_no":""},{"id":"dek_1773254096444_54","tur":"odeme","tutar":1000,"tarih":"2023-08-11","saat":"","aciklama":"ÖDENEN PARA","no":"0028395","belge_no":""},{"id":"dek_1773254096444_58","tur":"alacak","tutar":4309.44,"tarih":"2023-08-17","saat":"","aciklama":"ALINAN MALZEME","no":"0028684","belge_no":""},{"id":"dek_1773254096444_59","tur":"odeme","tutar":1000,"tarih":"2023-08-18","saat":"","aciklama":"ÖDENEN PARA","no":"0028685","belge_no":""},{"id":"dek_1773254096444_60","tur":"odeme","tutar":500,"tarih":"2023-08-25","saat":"","aciklama":"ÖDENEN PARA","no":"0028938","belge_no":""},{"id":"dek_1773254096444_61","tur":"odeme","tutar":1500,"tarih":"2023-09-01","saat":"","aciklama":"ÖDENEN PARA","no":"0029101","belge_no":""},{"id":"dek_1773254096444_62","tur":"odeme","tutar":500,"tarih":"2023-09-08","saat":"","aciklama":"ÖDENEN PARA","no":"0029278","belge_no":""},{"id":"dek_1773254096444_63","tur":"odeme","tutar":1500,"tarih":"2023-09-15","saat":"","aciklama":"ÖDENEN PARA","no":"0029433","belge_no":""},{"id":"dek_1773254096444_64","tur":"odeme","tutar":600,"tarih":"2023-09-22","saat":"","aciklama":"ÖDENEN PARA","no":"0029625","belge_no":""},{"id":"dek_1773254096444_65","tur":"alacak","tutar":1447.2,"tarih":"2023-09-22","saat":"","aciklama":"ALINAN MALZEME","no":"0029627","belge_no":""},{"id":"dek_1773254096444_66","tur":"odeme","tutar":500,"tarih":"2023-09-29","saat":"","aciklama":"ÖDENEN PARA","no":"0029881","belge_no":""},{"id":"dek_1773254096444_67","tur":"odeme","tutar":500,"tarih":"2023-10-06","saat":"","aciklama":"ÖDENEN PARA","no":"0030093","belge_no":""},{"id":"dek_1773254096444_68","tur":"odeme","tutar":1000,"tarih":"2023-10-13","saat":"","aciklama":"ÖDENEN PARA","no":"0031099","belge_no":""},{"id":"dek_1773254096444_69","tur":"alacak","tutar":3316.13,"tarih":"2023-10-20","saat":"","aciklama":"ALINAN MALZEME","no":"0030593","belge_no":""},{"id":"dek_1773254096444_70","tur":"odeme","tutar":1000,"tarih":"2023-10-20","saat":"","aciklama":"ÖDENEN PARA","no":"0030594","belge_no":""},{"id":"dek_1773254096444_71","tur":"odeme","tutar":1000,"tarih":"2023-10-27","saat":"","aciklama":"ÖDENEN PARA","no":"0030823","belge_no":""},{"id":"dek_1773254096444_72","tur":"odeme","tutar":1500,"tarih":"2023-11-03","saat":"","aciklama":"ÖDENEN PARA","no":"0031098","belge_no":""},{"id":"dek_1773254096444_73","tur":"alacak","tutar":1619.99,"tarih":"2023-11-04","saat":"","aciklama":"ALINAN MALZEME","no":"0031264","belge_no":""},{"id":"dek_1773254096444_74","tur":"odeme","tutar":500,"tarih":"2023-11-10","saat":"","aciklama":"ÖDENEN PARA","no":"0031265","belge_no":""},{"id":"dek_1773254096444_75","tur":"odeme","tutar":700,"tarih":"2023-11-17","saat":"","aciklama":"ÖDENEN PARA","no":"0031565","belge_no":""},{"id":"dek_1773254096444_76","tur":"alacak","tutar":4417.24,"tarih":"2023-12-22","saat":"","aciklama":"ALINAN MALZEME","no":"0032554","belge_no":""},{"id":"dek_1773254096444_77","tur":"odeme","tutar":1000,"tarih":"2023-12-22","saat":"","aciklama":"ÖDENEN PARA","no":"0032555","belge_no":""},{"id":"dek_1773254096444_78","tur":"odeme","tutar":1000,"tarih":"2023-12-29","saat":"","aciklama":"ÖDENEN PARA","no":"0032778","belge_no":""},{"id":"dek_1773254096444_79","tur":"odeme","tutar":1000,"tarih":"2024-01-05","saat":"","aciklama":"ÖDENEN PARA","no":"0032968","belge_no":""},{"id":"dek_1773254096444_80","tur":"alacak","tutar":1875,"tarih":"2024-01-06","saat":"","aciklama":"ALINAN MALZEME","no":"0033191","belge_no":""},{"id":"dek_1773254096444_81","tur":"odeme","tutar":600,"tarih":"2024-01-19","saat":"","aciklama":"ÖDENEN PARA","no":"0033359","belge_no":""},{"id":"dek_1773254096444_82","tur":"odeme","tutar":1875,"tarih":"2024-01-26","saat":"","aciklama":"ÖDENEN PARA","no":"0033538","belge_no":""},{"id":"dek_1773254096444_83","tur":"odeme","tutar":835,"tarih":"2024-02-02","saat":"","aciklama":"ÖDENEN PARA","no":"0033751","belge_no":""},{"id":"dek_1773254096444_84","tur":"alacak","tutar":4259.22,"tarih":"2024-03-22","saat":"","aciklama":"ALINAN MALZEME","no":"0035014","belge_no":""},{"id":"dek_1773254096444_85","tur":"odeme","tutar":1000,"tarih":"2024-03-29","saat":"","aciklama":"ÖDENEN PARA","no":"0035160","belge_no":""},{"id":"dek_1773254096444_86","tur":"alacak","tutar":288,"tarih":"2024-03-30","saat":"","aciklama":"ALINAN MALZEME","no":"0035288","belge_no":""},{"id":"dek_1773254096444_87","tur":"odeme","tutar":1000,"tarih":"2024-04-05","saat":"","aciklama":"ÖDENEN PARA","no":"0035307","belge_no":""},{"id":"dek_1773254096444_88","tur":"odeme","tutar":1000,"tarih":"2024-04-19","saat":"","aciklama":"ÖDENEN PARA","no":"0035512","belge_no":""},{"id":"dek_1773254096444_89","tur":"odeme","tutar":1000,"tarih":"2024-04-26","saat":"","aciklama":"ÖDENEN PARA","no":"0035718","belge_no":""},{"id":"dek_1773254096444_90","tur":"odeme","tutar":550,"tarih":"2024-05-03","saat":"","aciklama":"ÖDENEN PARA","no":"0035894","belge_no":""},{"id":"dek_1773254096444_91","tur":"alacak","tutar":1382.4,"tarih":"2024-05-24","saat":"","aciklama":"ALINAN MALZEME","no":"0036343","belge_no":""},{"id":"dek_1773254096444_92","tur":"alacak","tutar":3402.4,"tarih":"2024-05-24","saat":"","aciklama":"ALINAN MALZEME","no":"0036481","belge_no":""},{"id":"dek_1773254096444_93","tur":"odeme","tutar":1000,"tarih":"2024-05-31","saat":"","aciklama":"ÖDENEN PARA","no":"0036529","belge_no":""},{"id":"dek_1773254096444_94","tur":"odeme","tutar":800,"tarih":"2024-06-07","saat":"","aciklama":"ÖDENEN PARA","no":"0036763","belge_no":""},{"id":"dek_1773254096444_95","tur":"odeme","tutar":1000,"tarih":"2024-06-14","saat":"","aciklama":"ÖDENEN PARA","no":"0036926","belge_no":""},{"id":"dek_1773254096444_96","tur":"odeme","tutar":1000,"tarih":"2024-06-28","saat":"","aciklama":"ÖDENEN PARA","no":"0037127","belge_no":""},{"id":"dek_1773254096444_97","tur":"alacak","tutar":3350,"tarih":"2024-07-05","saat":"","aciklama":"VOLKAN TRAJLI KİLİT 20  ADET 167,50 TL DEN","no":"0037313","belge_no":""},{"id":"dek_1773254096444_98","tur":"odeme","tutar":1000,"tarih":"2024-07-05","saat":"","aciklama":"ÖDENEN PARA","no":"0037314","belge_no":""},{"id":"dek_1773254096444_99","tur":"odeme","tutar":1000,"tarih":"2024-07-12","saat":"","aciklama":"ÖDENEN PARA","no":"0037592","belge_no":""},{"id":"dek_1773254096444_100","tur":"odeme","tutar":1050,"tarih":"2024-07-19","saat":"","aciklama":"ÖDENEN PARA","no":"0037841","belge_no":""},{"id":"dek_1773254096444_101","tur":"odeme","tutar":1297,"tarih":"2024-07-26","saat":"","aciklama":"ÖDENEN PARA","no":"0038014","belge_no":""},{"id":"dek_1773254096444_102","tur":"alacak","tutar":527.9,"tarih":"2024-08-10","saat":"","aciklama":"ALINAN MALZEME","no":"0038515","belge_no":""},{"id":"dek_1773254096444_103","tur":"odeme","tutar":600,"tarih":"2024-08-16","saat":"","aciklama":"ÖDENEN PARA","no":"0038516","belge_no":""},{"id":"dek_1773254096444_104","tur":"alacak","tutar":19566.36,"tarih":"2024-09-13","saat":"","aciklama":"ALINAN MALZEME","no":"0039365","belge_no":""},{"id":"dek_1773254096444_105","tur":"alacak","tutar":4125.42,"tarih":"2024-09-17","saat":"","aciklama":"ALINAN MALZEME","no":"0039366","belge_no":""},{"id":"dek_1773254096444_106","tur":"alacak","tutar":3096,"tarih":"2024-09-21","saat":"","aciklama":"ALINAN MALZEME","no":"0039507","belge_no":""},{"id":"dek_1773254096444_107","tur":"odeme","tutar":23605,"tarih":"2024-09-26","saat":"","aciklama":"İŞİM K.KARTI İLE ÖDEDİM 3 TAKSİT ATLI HIRDAVAT","no":"0039489","belge_no":""},{"id":"dek_1773254096444_108","tur":"odeme","tutar":3096,"tarih":"2024-09-26","saat":"","aciklama":"ZİRAT BANKKART İLE ÖDEDİM TEK ÇEKİM","no":"0039508","belge_no":""},{"id":"dek_1773254096444_109","tur":"alacak","tutar":1522.2,"tarih":"2024-10-09","saat":"","aciklama":"ALINAN MALZEME","no":"0039826","belge_no":""},{"id":"dek_1773254096444_110","tur":"odeme","tutar":1500,"tarih":"2024-11-01","saat":"","aciklama":"ÖDENEN PARA","no":"0040361","belge_no":""},{"id":"dek_1773254096444_111","tur":"alacak","tutar":11953.74,"tarih":"2024-12-20","saat":"","aciklama":"ALINAN MALZEME","no":"0041845","belge_no":""},{"id":"dek_1773254096444_112","tur":"odeme","tutar":1000,"tarih":"2024-12-27","saat":"","aciklama":"ÖDENEN PARA","no":"0042075","belge_no":""},{"id":"dek_1773254096444_117","tur":"odeme","tutar":20000,"tarih":"2025-01-03","saat":"","aciklama":"AXESS K.KARTINDAN ÖDEDİM 6 TAKSİT","no":"0042234","belge_no":""},{"id":"dek_1773254096444_118","tur":"alacak","tutar":835.2,"tarih":"2025-01-03","saat":"","aciklama":"ALINAN MALZEME","no":"0042412","belge_no":""},{"id":"dek_1773254096444_119","tur":"alacak","tutar":5004.43,"tarih":"2025-02-14","saat":"","aciklama":"ALINAN MALZEME","no":"0043080","belge_no":""},{"id":"dek_1773254096444_120","tur":"alacak","tutar":7542.72,"tarih":"2025-02-21","saat":"","aciklama":"ALINAN MALZEME","no":"0043267","belge_no":""},{"id":"dek_1773254096444_121","tur":"odeme","tutar":4357.82,"tarih":"2025-03-17","saat":"","aciklama":"GARANTİ K.KARTI ÇEKTİM 1048","no":"0043927","belge_no":""},{"id":"dek_1773254096444_122","tur":"alacak","tutar":1987.96,"tarih":"2025-03-28","saat":"","aciklama":"ALINAN MALZEME","no":"0044335","belge_no":""},{"id":"dek_1773254096444_123","tur":"odeme","tutar":1987.96,"tarih":"2025-04-25","saat":"","aciklama":"ÖDENEN PARA","no":"0044967","belge_no":""},{"id":"dek_1773254096445_124","tur":"alacak","tutar":1000,"tarih":"2025-10-17","saat":"","aciklama":"DMAX ANALOG TERMOMETRE 10 ADET 100,00 TL DEN","no":"0049279","belge_no":""},{"id":"dek_1773254096445_125","tur":"odeme","tutar":1000,"tarih":"2025-10-17","saat":"","aciklama":"ÖDENEN PARA","no":"0049280","belge_no":""},{"id":"dek_1773254096445_126","tur":"alacak","tutar":8827.92,"tarih":"2025-11-18","saat":"","aciklama":"ALINAN MALZEME","no":"0050081","belge_no":""},{"id":"dek_1773254096445_127","tur":"odeme","tutar":10000,"tarih":"2025-12-05","saat":"","aciklama":"AXESS K.KARTI ÇEKTİM 6 TAKSİT","no":"0050417","belge_no":""},{"id":"dek_1773254096445_128","tur":"alacak","tutar":4185.42,"tarih":"2026-01-29","saat":"","aciklama":"ALINAN MALZEME","no":"0051650","belge_no":""},{"id":"dek_1773254096445_129","tur":"odeme","tutar":30000,"tarih":"2026-02-06","saat":"","aciklama":"WORLD K.KARTI ÇEKTİM 6 TAKSİT KAMPANYA","no":"0051862","belge_no":""},{"id":"dek_1773254096445_130","tur":"alacak","tutar":2097.68,"tarih":"2026-02-16","saat":"","aciklama":"ALINAN MALZEME","no":"0052144","belge_no":""},{"id":"dek_1773254096445_131","tur":"alacak","tutar":3872.72,"tarih":"2026-02-25","saat":"","aciklama":"ALINAN MALZEME","no":"0052305","belge_no":""}]