[{"id":"dek_1773254786127_6","tur":"alacak","tutar":10000,"tarih":"2020-01-12","saat":"","aciklama":"ALDIĞIM MALZEME","no":"0002821","belge_no":""},{"id":"dek_1773254786127_7","tur":"odeme","tutar":3000,"tarih":"2020-01-12","saat":"","aciklama":"ÖDENEN PARA","no":"0002822","belge_no":""},{"id":"dek_1773254786127_8","tur":"odeme","tutar":500,"tarih":"2020-03-16","saat":"","aciklama":"ÖDENEN PARA","no":"0003534","belge_no":""},{"id":"dek_1773254786127_9","tur":"odeme","tutar":2000,"tarih":"2020-05-22","saat":"","aciklama":"ÖDENEN PARA","no":"0004368","belge_no":""},{"id":"dek_1773254786127_10","tur":"odeme","tutar":500,"tarih":"2020-08-19","saat":"","aciklama":"ÖDENEN PARA","no":"0005699","belge_no":""},{"id":"dek_1773254786127_11","tur":"odeme","tutar":500,"tarih":"2020-09-05","saat":"","aciklama":"ÖDENEN PARA","no":"0006004","belge_no":""},{"id":"dek_1773254786127_12","tur":"odeme","tutar":500,"tarih":"2020-10-04","saat":"","aciklama":"ÖDENEN PARA","no":"0006584","belge_no":""},{"id":"dek_1773254786127_13","tur":"odeme","tutar":500,"tarih":"2020-10-24","saat":"","aciklama":"ÖDENEN PARA","no":"0006988","belge_no":""},{"id":"dek_1773254786127_14","tur":"odeme","tutar":500,"tarih":"2020-12-18","saat":"","aciklama":"ÖDENEN PARA","no":"0008005","belge_no":""},{"id":"dek_1773254786127_15","tur":"odeme","tutar":2000,"tarih":"2021-02-19","saat":"","aciklama":"ÖDENEN PARA","no":"0009045","belge_no":""},{"id":"dek_1773254786127_16","tur":"borc","tutar":545,"tarih":"2022-10-05","saat":"","aciklama":"BAKİYE","no":"0019894","belge_no":""},{"id":"dek_1773254786127_17","tur":"tahsilat","tutar":545,"tarih":"2022-11-03","saat":"","aciklama":"ALINAN PARA","no":"0020723","belge_no":""},{"id":"dek_1773254786127_18","tur":"borc","tutar":64,"tarih":"2022-11-26","saat":"","aciklama":"1/2*1/2 NİPELLİ FLEX 50 CM 2 ADET","no":"0021378","belge_no":""},{"id":"dek_1773254786127_19","tur":"borc","tutar":12,"tarih":"2022-11-26","saat":"","aciklama":"İZYAPI ŞOFBEN ASMA VİDASI 1 PAKET","no":"0021379","belge_no":""},{"id":"dek_1773254786127_20","tur":"tahsilat","tutar":76,"tarih":"2022-12-01","saat":"","aciklama":"ALINAN PARA","no":"0021479","belge_no":""},{"id":"dek_1773254786127_21","tur":"borc","tutar":150,"tarih":"2023-03-18","saat":"","aciklama":"ARAL KALİTELİ DUŞ HORTUMU 1 ADET","no":"0023955","belge_no":""},{"id":"dek_1773254786127_22","tur":"borc","tutar":25,"tarih":"2023-03-18","saat":"","aciklama":"DUŞ ELCİĞİ 1 ADET","no":"0023956","belge_no":""},{"id":"dek_1773254786127_23","tur":"alacak","tutar":260,"tarih":"2023-03-25","saat":"","aciklama":"İŞÇİLİK","no":"0024161","belge_no":""},{"id":"dek_1773254786127_24","tur":"borc","tutar":12.5,"tarih":"2023-03-25","saat":"","aciklama":"GIRTLAK HORTUM 0,5 METRE","no":"0024162","belge_no":""},{"id":"dek_1773254786127_25","tur":"borc","tutar":10,"tarih":"2023-03-25","saat":"","aciklama":"3/4 GARDEN HORTUM 40 CM","no":"0024163","belge_no":""},{"id":"dek_1773254786127_26","tur":"borc","tutar":25,"tarih":"2023-03-25","saat":"","aciklama":"YER SİFONU 32 LİK KROM 1 ADET","no":"0024164","belge_no":""},{"id":"dek_1773254786127_27","tur":"borc","tutar":6,"tarih":"2023-03-25","saat":"","aciklama":"ADAPTÖR CONTA 2 ADET","no":"0024165","belge_no":""},{"id":"dek_1773254786127_28","tur":"borc","tutar":7.5,"tarih":"2023-03-25","saat":"","aciklama":"50*45 DİRSEK 1 ADET","no":"0024166","belge_no":""},{"id":"dek_1773254786127_29","tur":"borc","tutar":13.5,"tarih":"2023-03-25","saat":"","aciklama":"50*50 ÇATAL 1 ADET","no":"0024167","belge_no":""},{"id":"dek_1773254786127_30","tur":"borc","tutar":3,"tarih":"2023-03-25","saat":"","aciklama":"18*25 HORTUM KELEPÇESİ 1 ADET","no":"0024168","belge_no":""},{"id":"dek_1773254786127_31","tur":"borc","tutar":27.5,"tarih":"2023-03-25","saat":"","aciklama":"BEYAZ ÇİMENTO 3 KG","no":"0024177","belge_no":""},{"id":"dek_1773254786127_32","tur":"tahsilat","tutar":20,"tarih":"2023-04-01","saat":"","aciklama":"ALINAN PARA","no":"0024408","belge_no":""},{"id":"dek_1773254786127_33","tur":"borc","tutar":100,"tarih":"2023-04-15","saat":"","aciklama":"ÖZBEST DUŞ TAKIMI 1 ADET","no":"0024844","belge_no":""},{"id":"dek_1773254786127_34","tur":"borc","tutar":60,"tarih":"2023-04-15","saat":"","aciklama":"DUŞ KORDONU 2 MT 1 ADET","no":"0024846","belge_no":""},{"id":"dek_1773254786127_35","tur":"borc","tutar":10,"tarih":"2023-04-15","saat":"","aciklama":"1/2 NİPEL SARI 1 ADET","no":"0024847","belge_no":""},{"id":"dek_1773254786127_36","tur":"borc","tutar":90,"tarih":"2023-04-15","saat":"","aciklama":"CERESİT ŞEFFAF SİLİKON 2 ADET","no":"0024848","belge_no":""},{"id":"dek_1773254786127_37","tur":"borc","tutar":40,"tarih":"2023-04-15","saat":"","aciklama":"DUŞ YÖNLENDİRİCİ 1 ADET","no":"0024849","belge_no":""},{"id":"dek_1773254786127_38","tur":"borc","tutar":55,"tarih":"2023-04-15","saat":"","aciklama":"KARTUŞ 1 ADET","no":"0024850","belge_no":""},{"id":"dek_1773254786127_39","tur":"borc","tutar":40,"tarih":"2023-04-15","saat":"","aciklama":"DONAU 50 LİK ÇIKIŞLI LAVABO SİFONU 1 ADET","no":"0024853","belge_no":""},{"id":"dek_1773254786127_40","tur":"borc","tutar":120,"tarih":"2023-05-16","saat":"","aciklama":"DANAU ÇÖPMAK TAŞMALIKLI EVYE SİFONU 1 ADET","no":"0025712","belge_no":""},{"id":"dek_1773254786127_41","tur":"tahsilat","tutar":515,"tarih":"2023-09-15","saat":"","aciklama":"ALINAN PARA","no":"0031359","belge_no":""},{"id":"dek_1773254786127_42","tur":"borc","tutar":110,"tarih":"2023-11-01","saat":"","aciklama":"ARAL KISA MUSLUK 1 ADET","no":"0031031","belge_no":""},{"id":"dek_1773254786127_43","tur":"borc","tutar":290,"tarih":"2023-11-01","saat":"","aciklama":"JAPAR GÖMME REZERVUAR FİLETÖRÜ 1 ADET","no":"0031032","belge_no":""},{"id":"dek_1773254786127_44","tur":"borc","tutar":1250,"tarih":"2023-11-13","saat":"","aciklama":"BATARYA 1 ADET","no":"0031360","belge_no":""},{"id":"dek_1773254786127_45","tur":"borc","tutar":50,"tarih":"2023-11-13","saat":"","aciklama":"JAPAR GÖMME  BOŞALTMA REKORU 1 ADET","no":"0031362","belge_no":""},{"id":"dek_1773254786127_46","tur":"borc","tutar":185,"tarih":"2023-11-13","saat":"","aciklama":"TEOS İÇ TAKIM 1 ADET","no":"0031364","belge_no":""},{"id":"dek_1773254786127_47","tur":"borc","tutar":800,"tarih":"2023-11-13","saat":"","aciklama":"ROBOT DUŞ LÜX 1 ADET","no":"0031365","belge_no":""},{"id":"dek_1773254786127_48","tur":"tahsilat","tutar":185,"tarih":"2023-11-22","saat":"","aciklama":"ALINAN PARA","no":"0031735","belge_no":""},{"id":"dek_1773254786127_49","tur":"borc","tutar":3,"tarih":"2023-11-22","saat":"","aciklama":"20 MM MANŞON 2 ADET","no":"0031738","belge_no":""},{"id":"dek_1773254786127_50","tur":"borc","tutar":3,"tarih":"2023-11-22","saat":"","aciklama":"25 MM DİRSEK 1 ADET","no":"0031739","belge_no":""},{"id":"dek_1773254786127_51","tur":"borc","tutar":2.5,"tarih":"2023-11-22","saat":"","aciklama":"25 MM MANŞON 1 ADET","no":"0031740","belge_no":""},{"id":"dek_1773254786127_52","tur":"borc","tutar":60,"tarih":"2023-11-25","saat":"","aciklama":"CERESİT ŞEFFAF SİLİKON 1 ADET","no":"0031847","belge_no":""},{"id":"dek_1773254786127_53","tur":"borc","tutar":75,"tarih":"2023-11-25","saat":"","aciklama":"WELLY AKVARYUM SİLİKONU 1 ADET","no":"0031848","belge_no":""},{"id":"dek_1773254786127_54","tur":"borc","tutar":85,"tarih":"2023-11-25","saat":"","aciklama":"KÜVET KENAR ÇITASI 1 ADET","no":"0031849","belge_no":""},{"id":"dek_1773254786127_58","tur":"borc","tutar":220,"tarih":"2023-11-25","saat":"","aciklama":"AÇ KAPA ANKASTRE KAPAK TAKIMI 1 ADET","no":"0031855","belge_no":""},{"id":"dek_1773254786127_59","tur":"tahsilat","tutar":2948.5,"tarih":"2023-11-27","saat":"","aciklama":"ALINAN PARA","no":"0031890","belge_no":""},{"id":"dek_1773254786127_60","tur":"borc","tutar":220,"tarih":"2023-12-02","saat":"","aciklama":"İLHAN ÇAMAŞIR MUSLUĞU 1 ADET","no":"0032032","belge_no":""},{"id":"dek_1773254786127_61","tur":"borc","tutar":350,"tarih":"2023-12-16","saat":"","aciklama":"EVYE BATARYASI 1 ADET","no":"0032392","belge_no":""},{"id":"dek_1773254786127_62","tur":"borc","tutar":130,"tarih":"2023-12-16","saat":"","aciklama":"UZUN MUSLUK 1 ADET","no":"0032393","belge_no":""},{"id":"dek_1773254786127_63","tur":"borc","tutar":30,"tarih":"2023-12-16","saat":"","aciklama":"1/2\" TE 1 ADET","no":"0032394","belge_no":""},{"id":"dek_1773254786127_64","tur":"borc","tutar":20,"tarih":"2023-12-16","saat":"","aciklama":"1/2\" NİPEL 1 ADET","no":"0032395","belge_no":""},{"id":"dek_1773254786127_65","tur":"borc","tutar":20,"tarih":"2023-12-16","saat":"","aciklama":"50*50 TEK ÇATAL 1 ADET","no":"0032396","belge_no":""},{"id":"dek_1773254786127_66","tur":"borc","tutar":12,"tarih":"2023-12-16","saat":"","aciklama":"50*87 DİRSEK 1 ADET","no":"0032397","belge_no":""},{"id":"dek_1773254786127_67","tur":"borc","tutar":8,"tarih":"2023-12-16","saat":"","aciklama":"50 LİK ADAPTÖR 1 ADET","no":"0032398","belge_no":""},{"id":"dek_1773254786127_68","tur":"borc","tutar":650,"tarih":"2023-12-16","saat":"","aciklama":"BORU MAKASI 1 ADET","no":"0032399","belge_no":""},{"id":"dek_1773254786127_69","tur":"tahsilat","tutar":1000,"tarih":"2023-12-16","saat":"","aciklama":"ALINAN PARA","no":"0032400","belge_no":""},{"id":"dek_1773254786127_70","tur":"borc","tutar":120,"tarih":"2024-01-13","saat":"","aciklama":"İZYAPI KÖRÜKLÜ KADA 1 ADET","no":"0033206","belge_no":""},{"id":"dek_1773254786127_71","tur":"borc","tutar":20,"tarih":"2024-01-13","saat":"","aciklama":"TAHARET BORUSU 1 ADET","no":"0033207","belge_no":""},{"id":"dek_1773254786127_72","tur":"borc","tutar":45,"tarih":"2024-01-13","saat":"","aciklama":"3/8*3/8 FLEX 40 CM 1 ADET","no":"0033208","belge_no":""},{"id":"dek_1773254786127_73","tur":"borc","tutar":55,"tarih":"2024-01-13","saat":"","aciklama":"3/8*3/8 FLEX 50 CM 1 ADET","no":"0033209","belge_no":""},{"id":"dek_1773254786127_74","tur":"borc","tutar":90,"tarih":"2024-01-13","saat":"","aciklama":"GAZLI PİSTON 2 ADET","no":"0033210","belge_no":""},{"id":"dek_1773254786127_75","tur":"borc","tutar":4000,"tarih":"2024-01-17","saat":"","aciklama":"TURKUAZ TUVALET TAŞI 1 TAKIM","no":"0033303","belge_no":""},{"id":"dek_1773254786127_76","tur":"borc","tutar":200,"tarih":"2024-01-27","saat":"","aciklama":"VİSAM TEOS 1 ADET","no":"0033568","belge_no":""},{"id":"dek_1773254786127_77","tur":"borc","tutar":85,"tarih":"2024-01-27","saat":"","aciklama":"FORCE BORU SIZDIRMAZLIK 50 ML 1 ADET","no":"0033569","belge_no":""},{"id":"dek_1773254786127_78","tur":"borc","tutar":300,"tarih":"2024-01-27","saat":"","aciklama":"DOĞALGAZ FLEXİ 1,50 MT 1 ADET","no":"0033570","belge_no":""},{"id":"dek_1773254786127_79","tur":"borc","tutar":135,"tarih":"2024-02-03","saat":"","aciklama":"ÇÖPMAK TAŞMALIKLI EVYE SİFONU 1 ADET","no":"0033788","belge_no":""},{"id":"dek_1773254786127_80","tur":"borc","tutar":4,"tarih":"2024-02-03","saat":"","aciklama":"3,9*13 YSB MATKAP UÇLU VİDA 10 ADET","no":"0033789","belge_no":""},{"id":"dek_1773254786127_81","tur":"borc","tutar":12,"tarih":"2024-02-03","saat":"","aciklama":"5*60 SUNTA VİDASI 10 ADET","no":"0033790","belge_no":""},{"id":"dek_1773254786127_82","tur":"borc","tutar":3.5,"tarih":"2024-02-03","saat":"","aciklama":"8 MM ROKET DÜBEL 10 ADET","no":"0033791","belge_no":""},{"id":"dek_1773254786127_83","tur":"borc","tutar":2400,"tarih":"2024-02-08","saat":"","aciklama":"MURCEL ŞARJLI MATKAP 1 ADET","no":"0033939","belge_no":""},{"id":"dek_1773254786127_84","tur":"borc","tutar":100,"tarih":"2024-02-08","saat":"","aciklama":"ARAL TAHARET MUSLUĞU 1 ADET","no":"0033940","belge_no":""},{"id":"dek_1773254786127_85","tur":"borc","tutar":24,"tarih":"2024-02-08","saat":"","aciklama":"15*25 MASA GÖNYE 8 ADET","no":"0033941","belge_no":""},{"id":"dek_1773254786127_86","tur":"tahsilat","tutar":2500,"tarih":"2024-02-08","saat":"","aciklama":"ALINAN PARA","no":"0033943","belge_no":""},{"id":"dek_1773254786127_87","tur":"borc","tutar":650,"tarih":"2024-03-04","saat":"","aciklama":"NKP SİLİM ELEGANS 1 ADET","no":"0034539","belge_no":""},{"id":"dek_1773254786127_88","tur":"tahsilat","tutar":1000,"tarih":"2024-03-04","saat":"","aciklama":"ALINAN PARA","no":"0034540","belge_no":""},{"id":"dek_1773254786127_89","tur":"borc","tutar":125,"tarih":"2024-03-09","saat":"","aciklama":"JAPAR KÖRÜKLÜ KADA 1 ADET","no":"0034709","belge_no":""},{"id":"dek_1773254786127_90","tur":"borc","tutar":200,"tarih":"2024-03-09","saat":"","aciklama":"VİSAM TEOS 1 ADET","no":"0034710","belge_no":""},{"id":"dek_1773254786127_91","tur":"borc","tutar":20,"tarih":"2024-03-09","saat":"","aciklama":"TEFLON BANT 1 ADET","no":"0034712","belge_no":""},{"id":"dek_1773254786127_92","tur":"borc","tutar":450,"tarih":"2024-03-10","saat":"","aciklama":"SEREN KUĞU EVYE BATARYASI 1 ADET","no":"0034733","belge_no":""},{"id":"dek_1773254786127_93","tur":"tahsilat","tutar":345,"tarih":"2024-03-10","saat":"","aciklama":"ALINAN PARA","no":"0034734","belge_no":""},{"id":"dek_1773254786127_94","tur":"borc","tutar":120,"tarih":"2024-03-14","saat":"","aciklama":"JAPAR KÖRÜKLÜ KADA 1 ADET","no":"0034823","belge_no":""},{"id":"dek_1773254786127_95","tur":"borc","tutar":100,"tarih":"2024-03-14","saat":"","aciklama":"3/8*3/8 40 CM BRANŞMAN 2 ADET","no":"0034825","belge_no":""},{"id":"dek_1773254786127_96","tur":"borc","tutar":500,"tarih":"2024-03-16","saat":"","aciklama":"YÜCEL LAVABO BATARYASI 1 ADET","no":"0034871","belge_no":""},{"id":"dek_1773254786127_97","tur":"tahsilat","tutar":3000,"tarih":"2024-03-16","saat":"","aciklama":"ALINAN PARA","no":"0034876","belge_no":""},{"id":"dek_1773254786127_98","tur":"borc","tutar":85,"tarih":"2024-03-17","saat":"","aciklama":"FİLTRELİ ARA MUSLUK 1 ADET","no":"0034881","belge_no":""},{"id":"dek_1773254786127_99","tur":"borc","tutar":36,"tarih":"2024-03-17","saat":"","aciklama":"15*45 MASA GÖNYE 12 ADET","no":"0034885","belge_no":""},{"id":"dek_1773254786127_100","tur":"borc","tutar":14,"tarih":"2024-03-17","saat":"","aciklama":"4*18 SUNTA VİDASI 50 ADET","no":"0034886","belge_no":""},{"id":"dek_1773254786127_101","tur":"borc","tutar":65,"tarih":"2024-03-17","saat":"","aciklama":"AKFİX HIZLI YAPIŞTIRICI 200 ML 1 ADET","no":"0034887","belge_no":""},{"id":"dek_1773254786127_102","tur":"tahsilat","tutar":1000,"tarih":"2024-04-13","saat":"","aciklama":"ALINAN PARA","no":"0035385","belge_no":""},{"id":"dek_1773254786127_103","tur":"borc","tutar":100,"tarih":"2024-04-26","saat":"","aciklama":"DİRSEKLİ KÖRÜKLÜ KADA 1 ADET","no":"0035717","belge_no":""},{"id":"dek_1773254786127_104","tur":"borc","tutar":1500,"tarih":"2024-04-28","saat":"","aciklama":"ACESER ARITMALI EVYE BATARYASI 1 ADET","no":"0035764","belge_no":""},{"id":"dek_1773254786127_105","tur":"tahsilat","tutar":2000,"tarih":"2024-04-28","saat":"","aciklama":"ALINAN PARA","no":"0035766","belge_no":""},{"id":"dek_1773254786127_106","tur":"borc","tutar":35,"tarih":"2024-05-01","saat":"","aciklama":"YALE ANAHTAR 1 ADET","no":"0035831","belge_no":""},{"id":"dek_1773254786127_107","tur":"tahsilat","tutar":1000,"tarih":"2024-05-01","saat":"","aciklama":"ALINAN PARA","no":"0035832","belge_no":""},{"id":"dek_1773254786127_108","tur":"borc","tutar":160,"tarih":"2024-05-26","saat":"","aciklama":"SİSTA AKVARYUM SİLİKON 1 ADET","no":"0036393","belge_no":""},{"id":"dek_1773254786127_109","tur":"borc","tutar":65,"tarih":"2024-05-26","saat":"","aciklama":"CERESİT ŞEFFAF SİLİKON 1 ADET","no":"0036394","belge_no":""},{"id":"dek_1773254786127_110","tur":"borc","tutar":5,"tarih":"2024-05-26","saat":"","aciklama":"20*70 PİTON 2 ADET","no":"0036395","belge_no":""},{"id":"dek_1773254786127_111","tur":"borc","tutar":312,"tarih":"2024-06-04","saat":"","aciklama":"20*1/2 BATARYA APARATI 4 ADET","no":"0036616","belge_no":""},{"id":"dek_1773254786127_112","tur":"borc","tutar":540,"tarih":"2024-06-04","saat":"","aciklama":"25*1/2 DİŞİ DİRSEK 20 ADET","no":"0036617","belge_no":""},{"id":"dek_1773254786127_117","tur":"borc","tutar":320,"tarih":"2024-06-04","saat":"","aciklama":"25*1/2 DİŞİ TE 10 ADET","no":"0036618","belge_no":""},{"id":"dek_1773254786127_118","tur":"borc","tutar":110,"tarih":"2024-06-04","saat":"","aciklama":"25*1/2 DİŞİ ADAPTÖR 5 ADET","no":"0036619","belge_no":""},{"id":"dek_1773254786127_119","tur":"borc","tutar":60,"tarih":"2024-06-04","saat":"","aciklama":"25*20 MM REDÜDSİYON DİRSEK 10 ADET","no":"0036620","belge_no":""},{"id":"dek_1773254786127_120","tur":"borc","tutar":540,"tarih":"2024-06-04","saat":"","aciklama":"25 MM PPRC DİRSEK 120 ADET","no":"0036621","belge_no":""},{"id":"dek_1773254786127_121","tur":"borc","tutar":300,"tarih":"2024-06-04","saat":"","aciklama":"25 MM PPRC TE 50 ADET","no":"0036622","belge_no":""},{"id":"dek_1773254786127_122","tur":"borc","tutar":144,"tarih":"2024-06-04","saat":"","aciklama":"25 MM PPRC KAVİS 8 ADET","no":"0036623","belge_no":""},{"id":"dek_1773254786127_123","tur":"borc","tutar":35,"tarih":"2024-06-04","saat":"","aciklama":"25 MM PPRC MANŞON 10 ADET","no":"0036624","belge_no":""},{"id":"dek_1773254786127_124","tur":"borc","tutar":720,"tarih":"2024-06-04","saat":"","aciklama":"25 MM PPRC STOP VANA 6 ADET","no":"0036625","belge_no":""},{"id":"dek_1773254786127_125","tur":"borc","tutar":380,"tarih":"2024-06-04","saat":"","aciklama":"50/45 DİRSEK 40 ADET","no":"0036626","belge_no":""},{"id":"dek_1773254786127_126","tur":"borc","tutar":240,"tarih":"2024-06-04","saat":"","aciklama":"50/87 DİRSEK 20 ADET","no":"0036627","belge_no":""},{"id":"dek_1773254786127_127","tur":"borc","tutar":190,"tarih":"2024-06-04","saat":"","aciklama":"50/50 TEK ÇATAL 10 ADET","no":"0036628","belge_no":""},{"id":"dek_1773254786127_128","tur":"borc","tutar":130,"tarih":"2024-06-04","saat":"","aciklama":"50/150 PVC 10 ADET","no":"0036629","belge_no":""},{"id":"dek_1773254786127_129","tur":"borc","tutar":165,"tarih":"2024-06-04","saat":"","aciklama":"70/45 DİRSEK 10 ADET","no":"0036630","belge_no":""},{"id":"dek_1773254786127_130","tur":"borc","tutar":129,"tarih":"2024-06-04","saat":"","aciklama":"70/87 DİRSEK 6 ADET","no":"0036631","belge_no":""},{"id":"dek_1773254786127_131","tur":"borc","tutar":56,"tarih":"2024-06-04","saat":"","aciklama":"70/50 TEK ÇATAL 2 ADET","no":"0036632","belge_no":""},{"id":"dek_1773254786127_132","tur":"borc","tutar":60,"tarih":"2024-06-04","saat":"","aciklama":"70/50 REDÜKSİYON 4 ADET","no":"0036633","belge_no":""},{"id":"dek_1773254786127_133","tur":"borc","tutar":126,"tarih":"2024-06-04","saat":"","aciklama":"100/70 TEK ÇATAL 2 ADET","no":"0036635","belge_no":""},{"id":"dek_1773254786127_134","tur":"borc","tutar":180,"tarih":"2024-06-04","saat":"","aciklama":"100/50 TEK ÇATAL 4 ADET","no":"0036636","belge_no":""},{"id":"dek_1773254786127_135","tur":"borc","tutar":320,"tarih":"2024-06-04","saat":"","aciklama":"100/45 DİRSEK 10 ADET","no":"0036637","belge_no":""},{"id":"dek_1773254786127_136","tur":"borc","tutar":92,"tarih":"2024-06-04","saat":"","aciklama":"125/100 REDÜKSİYON 2 ADET","no":"0036639","belge_no":""},{"id":"dek_1773254786127_137","tur":"borc","tutar":240,"tarih":"2024-06-04","saat":"","aciklama":"100/87 DİRSEK 6 ADET","no":"0036640","belge_no":""},{"id":"dek_1773254786127_138","tur":"tahsilat","tutar":1000,"tarih":"2024-06-20","saat":"","aciklama":"ALINAN PARA","no":"0036946","belge_no":""},{"id":"dek_1773254786127_139","tur":"tahsilat","tutar":5807.5,"tarih":"2024-07-08","saat":"","aciklama":"ALINAN PARA","no":"0038351","belge_no":""},{"id":"dek_1773254786127_140","tur":"borc","tutar":85,"tarih":"2024-08-09","saat":"","aciklama":"GÖMME AÇ-KAPA SALMASTRA UZİŞ 1 ADET","no":"0038368","belge_no":""},{"id":"dek_1773254786127_141","tur":"borc","tutar":320,"tarih":"2024-08-09","saat":"","aciklama":"İZELTAŞ 16*17 KOVAN ANAHTAR 1 ADET","no":"0038370","belge_no":""},{"id":"dek_1773254786127_142","tur":"borc","tutar":24,"tarih":"2024-08-12","saat":"","aciklama":"50/87 DİRSEK 2  ADET","no":"0038422","belge_no":""},{"id":"dek_1773254786127_143","tur":"borc","tutar":20,"tarih":"2024-08-12","saat":"","aciklama":"50/45 DİRSEK 2 ADET","no":"0038423","belge_no":""},{"id":"dek_1773254786127_144","tur":"borc","tutar":20,"tarih":"2024-08-12","saat":"","aciklama":"ADAPTÖR CONTA 2 ADET","no":"0038424","belge_no":""},{"id":"dek_1773254786127_145","tur":"borc","tutar":32.5,"tarih":"2024-08-12","saat":"","aciklama":"LAVABO AÇ 500 GR 1 ADET","no":"0038425","belge_no":""},{"id":"dek_1773254786127_146","tur":"borc","tutar":1000,"tarih":"2024-08-19","saat":"","aciklama":"HAY KUĞU EVYE BATARYASI 1 ADET","no":"0038565","belge_no":""},{"id":"dek_1773254786127_147","tur":"borc","tutar":110,"tarih":"2024-08-19","saat":"","aciklama":"3/8*3/8 NİPELLİ 30 CM FLEX 2 ADET","no":"0038567","belge_no":""},{"id":"dek_1773254786127_148","tur":"borc","tutar":150,"tarih":"2024-08-19","saat":"","aciklama":"ARAL TAHARET MUSLUĞU 1 ADET","no":"0038568","belge_no":""},{"id":"dek_1773254786127_149","tur":"tahsilat","tutar":1761,"tarih":"2024-08-19","saat":"","aciklama":"ALINAN PARA","no":"0038571","belge_no":""},{"id":"dek_1773254786127_150","tur":"borc","tutar":230,"tarih":"2024-08-19","saat":"","aciklama":"VİSAM TEOS 1 ADET","no":"0038574","belge_no":""},{"id":"dek_1773254786127_151","tur":"borc","tutar":150,"tarih":"2024-08-19","saat":"","aciklama":"ARAL TAHARET MUSLUĞU 1 ADET","no":"0038575","belge_no":""},{"id":"dek_1773254786127_152","tur":"borc","tutar":45,"tarih":"2024-08-19","saat":"","aciklama":"AKFİX TÜP SİLİKON 1 ADET","no":"0038576","belge_no":""},{"id":"dek_1773254786127_153","tur":"borc","tutar":10,"tarih":"2024-08-19","saat":"","aciklama":"1 CM KROM UZATMA 1 ADET","no":"0038577","belge_no":""},{"id":"dek_1773254786127_154","tur":"borc","tutar":10,"tarih":"2024-08-19","saat":"","aciklama":"KETEN 1 ADET","no":"0038579","belge_no":""},{"id":"dek_1773254786127_155","tur":"borc","tutar":90,"tarih":"2024-08-24","saat":"","aciklama":"PATTEX HIZLI YAPIŞTIRICI 200 ML 1 ADET","no":"0038705","belge_no":""},{"id":"dek_1773254786127_156","tur":"borc","tutar":350,"tarih":"2024-09-06","saat":"","aciklama":"HAY DUŞ KORDONU 1 ADET","no":"0039021","belge_no":""},{"id":"dek_1773254786127_157","tur":"borc","tutar":100,"tarih":"2024-09-06","saat":"","aciklama":"TOMBUL EL DUŞU 1 ADET","no":"0039024","belge_no":""},{"id":"dek_1773254786127_158","tur":"borc","tutar":230,"tarih":"2024-09-09","saat":"","aciklama":"VİSAM TEOS 1 ADET","no":"0039064","belge_no":""},{"id":"dek_1773254786127_159","tur":"borc","tutar":125,"tarih":"2024-09-09","saat":"","aciklama":"JAPAR KÖRÜKLÜ KADA 1 ADET","no":"0039065","belge_no":""},{"id":"dek_1773254786127_160","tur":"borc","tutar":385,"tarih":"2024-09-12","saat":"","aciklama":"20 MM KROM VANA 1 ADET","no":"0039177","belge_no":""},{"id":"dek_1773254786127_161","tur":"borc","tutar":130,"tarih":"2024-09-12","saat":"","aciklama":"BATARYA FLEXİ 50 CM 2 ADET","no":"0039180","belge_no":""},{"id":"dek_1773254786127_162","tur":"borc","tutar":10,"tarih":"2024-09-12","saat":"","aciklama":"DÜBEL VİDA 4 ADET","no":"0039182","belge_no":""},{"id":"dek_1773254786127_163","tur":"borc","tutar":150,"tarih":"2024-09-21","saat":"","aciklama":"SİSTA AKVARYUM SİLİKON 1 ADET","no":"0039390","belge_no":""},{"id":"dek_1773254786127_164","tur":"borc","tutar":100,"tarih":"2024-09-21","saat":"","aciklama":"NAVTEX ŞEFFAF SİLİKON 2 ADET","no":"0039391","belge_no":""},{"id":"dek_1773254786127_165","tur":"borc","tutar":30,"tarih":"2024-09-21","saat":"","aciklama":"FALÇATA YEDEĞİ 1 PAKET","no":"0039392","belge_no":""},{"id":"dek_1773254786127_166","tur":"borc","tutar":160,"tarih":"2024-09-21","saat":"","aciklama":"KÜVET KENAR ÇITASI 2 ADET","no":"0039393","belge_no":""},{"id":"dek_1773254786127_167","tur":"borc","tutar":390,"tarih":"2024-09-27","saat":"","aciklama":"SİSTA SİLİKON 3 ADET","no":"0039547","belge_no":""},{"id":"dek_1773254786127_168","tur":"borc","tutar":70,"tarih":"2024-09-27","saat":"","aciklama":"GÖNYE 250 MM  1 ADET","no":"0039548","belge_no":""},{"id":"dek_1773254786127_169","tur":"borc","tutar":60,"tarih":"2024-09-27","saat":"","aciklama":"FALÇATA 1 ADET","no":"0039549","belge_no":""},{"id":"dek_1773254786127_170","tur":"borc","tutar":80,"tarih":"2024-09-27","saat":"","aciklama":"KÜVET KENAR ÇITASI 1 ADET","no":"0039550","belge_no":""},{"id":"dek_1773254786127_171","tur":"borc","tutar":60,"tarih":"2024-10-02","saat":"","aciklama":"TEFLON BANT 3 ADET","no":"0039666","belge_no":""},{"id":"dek_1773254786127_176","tur":"tahsilat","tutar":1000,"tarih":"2024-10-02","saat":"","aciklama":"ALDIĞIMIZ PARA","no":"0039667","belge_no":""},{"id":"dek_1773254786127_177","tur":"borc","tutar":150,"tarih":"2024-10-04","saat":"","aciklama":"AÇ KAPA TAHARET MUSLUĞU 1 ADET","no":"0039726","belge_no":""},{"id":"dek_1773254786127_178","tur":"borc","tutar":460,"tarih":"2024-10-10","saat":"","aciklama":"VİSAM TEOS İÇ TAKIM 2 ADET","no":"0039855","belge_no":""},{"id":"dek_1773254786127_179","tur":"borc","tutar":240,"tarih":"2024-10-10","saat":"","aciklama":"JAPAR KÖRÜKLÜ KADA 2 ADET","no":"0039856","belge_no":""},{"id":"dek_1773254786127_180","tur":"tahsilat","tutar":1000,"tarih":"2024-10-12","saat":"","aciklama":"ALINAN PARA","no":"0039893","belge_no":""},{"id":"dek_1773254786127_181","tur":"borc","tutar":350,"tarih":"2024-10-12","saat":"","aciklama":"NORM İÇ TAKIM 1 ADET","no":"0039895","belge_no":""},{"id":"dek_1773254786127_182","tur":"borc","tutar":350,"tarih":"2024-10-17","saat":"","aciklama":"NORM İÇ TAKIM 1 ADET","no":"0040000","belge_no":""},{"id":"dek_1773254786128_183","tur":"borc","tutar":120,"tarih":"2024-10-17","saat":"","aciklama":"JAPAR KÖRÜKLÜ KADA 1 ADET","no":"0040003","belge_no":""},{"id":"dek_1773254786128_184","tur":"borc","tutar":80,"tarih":"2024-11-14","saat":"","aciklama":"35 LİK AYAKLI KARTUJ 1 ADET","no":"0040752","belge_no":""},{"id":"dek_1773254786128_185","tur":"borc","tutar":600,"tarih":"2024-11-23","saat":"","aciklama":"ROBOT DUŞ BAŞLIĞI 1 ADET","no":"0041024","belge_no":""},{"id":"dek_1773254786128_186","tur":"borc","tutar":40,"tarih":"2024-11-23","saat":"","aciklama":"50/45 DİRSEK 4 ADET","no":"0041025","belge_no":""},{"id":"dek_1773254786128_187","tur":"borc","tutar":24,"tarih":"2024-11-23","saat":"","aciklama":"50/87 DİRSEK 2 ADET","no":"0041026","belge_no":""},{"id":"dek_1773254786128_188","tur":"tahsilat","tutar":2000,"tarih":"2024-11-29","saat":"","aciklama":"ALINAN PARA","no":"0041205","belge_no":""},{"id":"dek_1773254786128_189","tur":"borc","tutar":275,"tarih":"2024-11-29","saat":"","aciklama":"JAPAR ANADOLU BASMALI İÇ TAKIM 1 ADET","no":"0041206","belge_no":""},{"id":"dek_1773254786128_190","tur":"borc","tutar":110,"tarih":"2024-11-29","saat":"","aciklama":"KLEPELİ ADAPTÖR 2 ADET","no":"0041207","belge_no":""},{"id":"dek_1773254786128_191","tur":"borc","tutar":20,"tarih":"2024-11-29","saat":"","aciklama":"ADAPTÖR CONTA 2 ADET","no":"0041208","belge_no":""},{"id":"dek_1773254786128_192","tur":"borc","tutar":50,"tarih":"2024-11-29","saat":"","aciklama":"TEFLON BANT 5 ADET","no":"0041209","belge_no":""},{"id":"dek_1773254786128_193","tur":"borc","tutar":25,"tarih":"2024-11-29","saat":"","aciklama":"TAMİR BANDI 1 ADET","no":"0041214","belge_no":""},{"id":"dek_1773254786128_194","tur":"borc","tutar":250,"tarih":"2024-12-07","saat":"","aciklama":"NOVA BASMALI REZERVUAR 1 ADET","no":"0041438","belge_no":""},{"id":"dek_1773254786128_195","tur":"borc","tutar":35,"tarih":"2024-12-07","saat":"","aciklama":"50*500 PVC 1 ADET","no":"0041440","belge_no":""},{"id":"dek_1773254786128_196","tur":"borc","tutar":49,"tarih":"2024-12-07","saat":"","aciklama":"50*1000 PVC 1 ADET","no":"0041441","belge_no":""},{"id":"dek_1773254786128_197","tur":"borc","tutar":12,"tarih":"2024-12-07","saat":"","aciklama":"50*90 DİRSEK 1 ADET","no":"0041442","belge_no":""},{"id":"dek_1773254786128_198","tur":"borc","tutar":40,"tarih":"2024-12-07","saat":"","aciklama":"50*45 DİRSEK 4 ADET","no":"0041443","belge_no":""},{"id":"dek_1773254786128_199","tur":"borc","tutar":20,"tarih":"2024-12-07","saat":"","aciklama":"50 LİK KELEPÇE 4 ADET","no":"0041444","belge_no":""},{"id":"dek_1773254786128_200","tur":"borc","tutar":85,"tarih":"2024-12-07","saat":"","aciklama":"DONAU LAVABO SİFONU 1 ADET","no":"0041445","belge_no":""},{"id":"dek_1773254786128_201","tur":"borc","tutar":10,"tarih":"2024-12-07","saat":"","aciklama":"50 LİK ADAPTÖR CONTA 1 ADET","no":"0041446","belge_no":""},{"id":"dek_1773254786128_202","tur":"borc","tutar":170,"tarih":"2024-12-07","saat":"","aciklama":"TEMİZ SU HORTUMU 4 MT 2 ADET","no":"0041468","belge_no":""},{"id":"dek_1773254786128_203","tur":"borc","tutar":20,"tarih":"2024-12-07","saat":"","aciklama":"50*50 TEK ÇATAL 1 ADET","no":"0041470","belge_no":""},{"id":"dek_1773254786128_204","tur":"borc","tutar":150,"tarih":"2024-12-07","saat":"","aciklama":"ÇAMAŞIR MUSLUĞU 1 ADET","no":"0041471","belge_no":""},{"id":"dek_1773254786128_205","tur":"borc","tutar":40,"tarih":"2024-12-12","saat":"","aciklama":"3/4\" SARI NİPEL 1 ADET","no":"0041567","belge_no":""},{"id":"dek_1773254786128_206","tur":"borc","tutar":135,"tarih":"2024-12-17","saat":"","aciklama":"FİLTRELİ ARA MUSLUK 1 ADET","no":"0041693","belge_no":""},{"id":"dek_1773254786128_207","tur":"borc","tutar":33,"tarih":"2024-12-17","saat":"","aciklama":"20*1/2 ERKEK DİRSEK 1  ADET","no":"0041694","belge_no":""},{"id":"dek_1773254786128_208","tur":"borc","tutar":26,"tarih":"2024-12-17","saat":"","aciklama":"20*1/2 DİŞİ DİRSEK 1 ADET","no":"0041695","belge_no":""},{"id":"dek_1773254786128_209","tur":"borc","tutar":35,"tarih":"2024-12-17","saat":"","aciklama":"1/2 GALVANİZ TE 1 ADET","no":"0041696","belge_no":""},{"id":"dek_1773254786128_210","tur":"borc","tutar":50,"tarih":"2024-12-17","saat":"","aciklama":"1/2 GALVANİZ NİPEL 2 ADET","no":"0041697","belge_no":""},{"id":"dek_1773254786128_211","tur":"borc","tutar":20,"tarih":"2024-12-17","saat":"","aciklama":"1/2 GALVANİZ MANŞON 1 ADET","no":"0041698","belge_no":""},{"id":"dek_1773254786128_212","tur":"borc","tutar":40,"tarih":"2024-12-17","saat":"","aciklama":"1/2 HORTUM REKORU 1 ADET","no":"0041699","belge_no":""},{"id":"dek_1773254786128_213","tur":"borc","tutar":5,"tarih":"2024-12-17","saat":"","aciklama":"HORTUM KELEPÇESİ 1 ADET","no":"0041700","belge_no":""},{"id":"dek_1773254786128_214","tur":"borc","tutar":160,"tarih":"2024-12-17","saat":"","aciklama":"1/2 KÜRESEL VANA 1 ADET","no":"0041701","belge_no":""},{"id":"dek_1773254786128_215","tur":"borc","tutar":70,"tarih":"2024-12-17","saat":"","aciklama":"LAVABO SİFONU 1 ADET","no":"0041703","belge_no":""},{"id":"dek_1773254786128_216","tur":"borc","tutar":5,"tarih":"2024-12-17","saat":"","aciklama":"ROKET DÜBEL 10 ADET","no":"0041704","belge_no":""},{"id":"dek_1773254786128_217","tur":"borc","tutar":20,"tarih":"2024-12-17","saat":"","aciklama":"6*70 SUNTA VİDASI 10 ADET","no":"0041705","belge_no":""},{"id":"dek_1773254786128_218","tur":"borc","tutar":20,"tarih":"2024-12-17","saat":"","aciklama":"ASKI TAKIMI 5 ADET","no":"0041706","belge_no":""},{"id":"dek_1773254786128_219","tur":"borc","tutar":195,"tarih":"2024-12-19","saat":"","aciklama":"ÇÖPMAK TAŞMALIKLI EVYE SİFONU 1 ADET","no":"0041771","belge_no":""},{"id":"dek_1773254786128_220","tur":"borc","tutar":200,"tarih":"2024-12-19","saat":"","aciklama":"FİLTRELİ ARA MUSLUK 2 ADET","no":"0041772","belge_no":""},{"id":"dek_1773254786128_221","tur":"borc","tutar":27.5,"tarih":"2024-12-19","saat":"","aciklama":"20MM DİRSEK 10 ADET","no":"0041773","belge_no":""},{"id":"dek_1773254786128_222","tur":"borc","tutar":2,"tarih":"2024-12-19","saat":"","aciklama":"20 MM MANŞON 1 ADET","no":"0041777","belge_no":""},{"id":"dek_1773254786128_223","tur":"borc","tutar":52,"tarih":"2024-12-19","saat":"","aciklama":"20*1/2 DİŞİ TE 2 ADET","no":"0041778","belge_no":""},{"id":"dek_1773254786128_224","tur":"borc","tutar":52,"tarih":"2024-12-19","saat":"","aciklama":"20*1/2 DİŞİ DİRSEK 2 ADET","no":"0041779","belge_no":""},{"id":"dek_1773254786128_225","tur":"borc","tutar":8,"tarih":"2024-12-19","saat":"","aciklama":"20 MM KELEPÇE 4 ADET","no":"0041780","belge_no":""},{"id":"dek_1773254786128_226","tur":"borc","tutar":20,"tarih":"2024-12-19","saat":"","aciklama":"50*50 TEK ÇATAL 1 ADET","no":"0041781","belge_no":""},{"id":"dek_1773254786128_227","tur":"borc","tutar":20,"tarih":"2024-12-19","saat":"","aciklama":"50*45 DİRSEK 2 ADET","no":"0041782","belge_no":""},{"id":"dek_1773254786128_228","tur":"borc","tutar":2,"tarih":"2024-12-19","saat":"","aciklama":"20 MM TAPA 1 ADET","no":"0041783","belge_no":""},{"id":"dek_1773254786128_229","tur":"borc","tutar":60,"tarih":"2024-12-19","saat":"","aciklama":"ŞEFFAF SLİKON 1 ADET","no":"0041785","belge_no":""},{"id":"dek_1773254786128_230","tur":"borc","tutar":10,"tarih":"2024-12-19","saat":"","aciklama":"1\"TRİFONLU KELEPÇE 1 ADET","no":"0041786","belge_no":""},{"id":"dek_1773254786128_235","tur":"borc","tutar":25,"tarih":"2024-12-19","saat":"","aciklama":"1/2 HORTUM UCU 1 ADET","no":"0041788","belge_no":""},{"id":"dek_1773254786128_236","tur":"borc","tutar":20,"tarih":"2024-12-19","saat":"","aciklama":"3/8 HORTUM UCU 1 ADET","no":"0041789","belge_no":""},{"id":"dek_1773254786128_237","tur":"borc","tutar":10,"tarih":"2024-12-19","saat":"","aciklama":"HSS MATKAP UCU 5 MM 1 ADET","no":"0041790","belge_no":""},{"id":"dek_1773254786128_238","tur":"tahsilat","tutar":2000,"tarih":"2024-12-21","saat":"","aciklama":"ALINAN PARA","no":"0041901","belge_no":""},{"id":"dek_1773254786128_239","tur":"borc","tutar":2427,"tarih":"2025-01-02","saat":"","aciklama":"ALDIKLARI MALZEME","no":"0042201","belge_no":""},{"id":"dek_1773254786128_240","tur":"borc","tutar":450,"tarih":"2025-01-04","saat":"","aciklama":"ARAL TAHARET MUSLUĞU 3 ADET","no":"0042245","belge_no":""},{"id":"dek_1773254786128_241","tur":"borc","tutar":50,"tarih":"2025-01-04","saat":"","aciklama":"50*1000 PVC 1 ADET","no":"0042246","belge_no":""},{"id":"dek_1773254786128_242","tur":"borc","tutar":5,"tarih":"2025-01-04","saat":"","aciklama":"50 LİK PLASTİK KELEPÇE 1 ADET","no":"0042247","belge_no":""},{"id":"dek_1773254786128_243","tur":"borc","tutar":130,"tarih":"2025-01-04","saat":"","aciklama":"3/8*3/8 FLEX 50 CM 2 ADET","no":"0042248","belge_no":""},{"id":"dek_1773254786128_244","tur":"borc","tutar":500,"tarih":"2025-01-24","saat":"","aciklama":"OKYANUS MİX LAVABO BATARYASI 1 ADET","no":"0042720","belge_no":""},{"id":"dek_1773254786128_245","tur":"borc","tutar":80,"tarih":"2025-01-24","saat":"","aciklama":"DONAU LAVABO SİFONU 1 ADET","no":"0042721","belge_no":""},{"id":"dek_1773254786128_246","tur":"borc","tutar":10,"tarih":"2025-01-24","saat":"","aciklama":"ADAPTÖR CONTA 1 ADET","no":"0042722","belge_no":""},{"id":"dek_1773254786128_247","tur":"borc","tutar":18471,"tarih":"2025-01-25","saat":"","aciklama":"ALINAN MALZEME","no":"0042745","belge_no":""},{"id":"dek_1773254786128_248","tur":"borc","tutar":270,"tarih":"2025-01-28","saat":"","aciklama":"VİSAM TEOS 1 ADET","no":"0042818","belge_no":""},{"id":"dek_1773254786128_249","tur":"borc","tutar":150,"tarih":"2025-01-28","saat":"","aciklama":"JAPAR KÖRÜKLÜ KADA 1 ADET","no":"0042819","belge_no":""},{"id":"dek_1773254786128_250","tur":"borc","tutar":10,"tarih":"2025-01-28","saat":"","aciklama":"ADAPTÖR CONTA 1 ADET","no":"0042822","belge_no":""},{"id":"dek_1773254786128_251","tur":"tahsilat","tutar":5400,"tarih":"2025-02-01","saat":"","aciklama":"ALINAN PARA","no":"0042950","belge_no":""},{"id":"dek_1773254786128_252","tur":"borc","tutar":150,"tarih":"2025-02-15","saat":"","aciklama":"JAPAR KÖRÜKLÜ KADA 1 ADET","no":"0043128","belge_no":""},{"id":"dek_1773254786128_253","tur":"borc","tutar":450,"tarih":"2025-02-15","saat":"","aciklama":"JAPAR ANADOLU BASMALI İÇ TAKIM 1 ADET","no":"0043129","belge_no":""},{"id":"dek_1773254786128_254","tur":"borc","tutar":600,"tarih":"2025-02-15","saat":"","aciklama":"ARAL TAHARET MUSLUĞU 2 ADET","no":"0043131","belge_no":""},{"id":"dek_1773254786128_255","tur":"tahsilat","tutar":6000,"tarih":"2025-02-15","saat":"","aciklama":"ALINAN PARA","no":"0043132","belge_no":""},{"id":"dek_1773254786128_256","tur":"borc","tutar":15,"tarih":"2025-03-02","saat":"","aciklama":"50*45 DİRSEK 1 ADET","no":"0043476","belge_no":""},{"id":"dek_1773254786128_257","tur":"borc","tutar":20,"tarih":"2025-03-02","saat":"","aciklama":"ADAPTÖR CONTA 2 ADET","no":"0043477","belge_no":""},{"id":"dek_1773254786128_258","tur":"tahsilat","tutar":10000,"tarih":"2025-03-02","saat":"","aciklama":"ALINAN PARA","no":"0043478","belge_no":""},{"id":"dek_1773254786128_259","tur":"tahsilat","tutar":4600,"tarih":"2025-03-22","saat":"","aciklama":"ALINAN PARA","no":"0044090","belge_no":""},{"id":"dek_1773254786128_260","tur":"borc","tutar":140,"tarih":"2025-03-23","saat":"","aciklama":"100*45 DİRSEK 3 ADET","no":"0044100","belge_no":""},{"id":"dek_1773254786128_261","tur":"borc","tutar":130,"tarih":"2025-03-23","saat":"","aciklama":"100*50 TEK ÇATAL 2 ADET","no":"0044101","belge_no":""},{"id":"dek_1773254786128_262","tur":"borc","tutar":160,"tarih":"2025-03-23","saat":"","aciklama":"100*1000 PVC 1 ADET","no":"0044102","belge_no":""},{"id":"dek_1773254786128_263","tur":"borc","tutar":135,"tarih":"2025-03-23","saat":"","aciklama":"100*250 PVC 2 ADET","no":"0044103","belge_no":""},{"id":"dek_1773254786128_264","tur":"borc","tutar":14,"tarih":"2025-03-23","saat":"","aciklama":"50*45 DİRSEK 1 ADET","no":"0044104","belge_no":""},{"id":"dek_1773254786128_265","tur":"borc","tutar":160,"tarih":"2025-03-23","saat":"","aciklama":"NP1 BEYAZ 1 ADET","no":"0044105","belge_no":""},{"id":"dek_1773254786128_266","tur":"borc","tutar":30,"tarih":"2025-03-26","saat":"","aciklama":"TAHARET ÇUBUĞU","no":"0044238","belge_no":""},{"id":"dek_1773254786128_267","tur":"borc","tutar":690,"tarih":"2025-03-26","saat":"","aciklama":"JAPAR PLASTİK BASMALI REZARVUAR 1 ADET","no":"0044239","belge_no":""},{"id":"dek_1773254786128_268","tur":"borc","tutar":120,"tarih":"2025-03-26","saat":"","aciklama":"TAHARET ÇUBUĞU 1 ADET","no":"0044240","belge_no":""},{"id":"dek_1773254786128_269","tur":"borc","tutar":110,"tarih":"2025-03-26","saat":"","aciklama":"TAHARET MUSLUĞU  1 ADET","no":"0044241","belge_no":""},{"id":"dek_1773254786128_270","tur":"tahsilat","tutar":1540,"tarih":"2025-03-26","saat":"","aciklama":"ALINAN PARA","no":"0044242","belge_no":""},{"id":"dek_1773254786128_271","tur":"borc","tutar":250,"tarih":"2025-04-15","saat":"","aciklama":"JAPAR ŞOK KAPATMALI FLATÖR 1 ADET","no":"0046072","belge_no":""},{"id":"dek_1773254786128_272","tur":"borc","tutar":1750,"tarih":"2025-04-15","saat":"","aciklama":"SİYAM EVYE BATARYASI","no":"0044675","belge_no":""},{"id":"dek_1773254786128_273","tur":"tahsilat","tutar":1750,"tarih":"2025-04-15","saat":"","aciklama":"ALINAN PARA","no":"0044676","belge_no":""},{"id":"dek_1773254786128_274","tur":"borc","tutar":350,"tarih":"2025-05-10","saat":"","aciklama":"JAPAR ANADOLU İÇ TAKIM 1 ADET","no":"0045418","belge_no":""},{"id":"dek_1773254786128_275","tur":"borc","tutar":150,"tarih":"2025-05-10","saat":"","aciklama":"JAPAR KÖRÜKLÜ KADA 1 ADET","no":"0045419","belge_no":""},{"id":"dek_1773254786128_276","tur":"borc","tutar":120,"tarih":"2025-06-01","saat":"","aciklama":"ŞENPRES FİLTRELİ ARA MUSLUK 1 ADET","no":"0046069","belge_no":""},{"id":"dek_1773254786128_277","tur":"borc","tutar":130,"tarih":"2025-06-01","saat":"","aciklama":"BATARYA FLEXİ 50 CM 2 ADET","no":"0046070","belge_no":""},{"id":"dek_1773254786128_278","tur":"tahsilat","tutar":250,"tarih":"2025-06-01","saat":"","aciklama":"ALINAN PARA","no":"0046071","belge_no":""},{"id":"dek_1773254786128_279","tur":"borc","tutar":20,"tarih":"2025-06-14","saat":"","aciklama":"100 LÜK PLASTİK KELEPÇE 1 ADET","no":"0046336","belge_no":""},{"id":"dek_1773254786128_280","tur":"borc","tutar":120,"tarih":"2025-06-14","saat":"","aciklama":"50 LİK KROM ALTTAN ÇIKIŞLI YER SİFONU 2 ADET","no":"0046337","belge_no":""},{"id":"dek_1773254786128_281","tur":"tahsilat","tutar":845,"tarih":"2025-09-29","saat":"","aciklama":"ALINAN PARA","no":"0048811","belge_no":""},{"id":"dek_1773254786128_282","tur":"borc","tutar":345,"tarih":"2025-09-30","saat":"","aciklama":"DONAU TAŞMALIKSIZ EVYE SİFONU 1 ADET","no":"0048876","belge_no":""},{"id":"dek_1773254786128_283","tur":"borc","tutar":200,"tarih":"2025-10-01","saat":"","aciklama":"LAVABO SİFONU 1 ADET","no":"0048861","belge_no":""},{"id":"dek_1773254786128_284","tur":"borc","tutar":285,"tarih":"2025-10-08","saat":"","aciklama":"ARTI ACEM TAHARET MUSLUĞU 1 ADET","no":"0049021","belge_no":""},{"id":"dek_1773254786128_285","tur":"borc","tutar":100,"tarih":"2025-10-11","saat":"","aciklama":"1/2 MİNİ KÜRESEL VANA 1 ADET","no":"0049112","belge_no":""},{"id":"dek_1773254786128_286","tur":"borc","tutar":40,"tarih":"2025-10-11","saat":"","aciklama":"1/2 HORTUM REKORU SARI 1 ADET","no":"0049113","belge_no":""},{"id":"dek_1773254786128_287","tur":"borc","tutar":5,"tarih":"2025-10-11","saat":"","aciklama":"HORTUM KELEPÇESİ 1 ADET","no":"0049114","belge_no":""},{"id":"dek_1773254786128_288","tur":"borc","tutar":32,"tarih":"2025-10-18","saat":"","aciklama":"20*1/2\" DİŞİ TE 1 ADET","no":"0049309","belge_no":""},{"id":"dek_1773254786128_289","tur":"borc","tutar":3,"tarih":"2025-10-18","saat":"","aciklama":"20 MM KÖRTAPA 1 ADET","no":"0049310","belge_no":""},{"id":"dek_1773254786128_294","tur":"borc","tutar":485,"tarih":"2025-10-24","saat":"","aciklama":"JAPAR TELESKOPİK FLATÖR 1 ADET","no":"0049453","belge_no":""},{"id":"dek_1773254786128_295","tur":"borc","tutar":15,"tarih":"2025-10-24","saat":"","aciklama":"TEFLON BANT 1 ADET","no":"0049454","belge_no":""},{"id":"dek_1773254786128_296","tur":"tahsilat","tutar":1000,"tarih":"2025-11-08","saat":"","aciklama":"ALINAN PARA","no":"0049754","belge_no":""},{"id":"dek_1773254786128_297","tur":"borc","tutar":85,"tarih":"2025-12-06","saat":"","aciklama":"SOUDAL SİLİKON 1 ADET","no":"0050439","belge_no":""},{"id":"dek_1773254786128_298","tur":"tahsilat","tutar":640,"tarih":"2025-12-19","saat":"","aciklama":"ALINAN PARA","no":"0050801","belge_no":""},{"id":"dek_1773254786128_299","tur":"borc","tutar":60,"tarih":"2025-12-19","saat":"","aciklama":"50*45 DİRSEK 4 ADET","no":"0050802","belge_no":""},{"id":"dek_1773254786128_300","tur":"borc","tutar":34,"tarih":"2025-12-19","saat":"","aciklama":"50*90 DİRSEK 2 ADET","no":"0050803","belge_no":""},{"id":"dek_1773254786128_301","tur":"borc","tutar":90,"tarih":"2025-12-19","saat":"","aciklama":"50*500 PVC BORU 2 ADET","no":"0050804","belge_no":""},{"id":"dek_1773254786128_302","tur":"borc","tutar":20,"tarih":"2025-12-19","saat":"","aciklama":"50 LİK KAYAR MANŞON 1 ADET","no":"0050805","belge_no":""},{"id":"dek_1773254786128_303","tur":"borc","tutar":30,"tarih":"2025-12-19","saat":"","aciklama":"50*50 TEK ÇATAL 1 ADET","no":"0050806","belge_no":""},{"id":"dek_1773254786128_304","tur":"borc","tutar":120,"tarih":"2025-12-19","saat":"","aciklama":"3/8*3/8 FLEX 100 CM 1 ADET","no":"0050807","belge_no":""},{"id":"dek_1773254786128_305","tur":"borc","tutar":70,"tarih":"2025-12-19","saat":"","aciklama":"3/8*3/8 NİPELLİ FLEX 30 CM 1 ADET","no":"0050808","belge_no":""},{"id":"dek_1773254786128_306","tur":"borc","tutar":290,"tarih":"2025-12-20","saat":"","aciklama":"25*3/4 ERKEK OYNARBAŞLI REKOR 2 ADET","no":"0050824","belge_no":""},{"id":"dek_1773254786128_307","tur":"borc","tutar":115,"tarih":"2025-12-20","saat":"","aciklama":"25 MM KÜRESEL VANA 1 ADET","no":"0050833","belge_no":""},{"id":"dek_1773254786128_308","tur":"borc","tutar":30,"tarih":"2025-12-20","saat":"","aciklama":"1*3/4 GALVANİZ REDÜKSİYON 1 ADET","no":"0050836","belge_no":""},{"id":"dek_1773254786128_309","tur":"tahsilat","tutar":400,"tarih":"2025-12-21","saat":"","aciklama":"ALINAN PARA","no":"0050837","belge_no":""},{"id":"dek_1773254786128_310","tur":"tahsilat","tutar":459,"tarih":"2025-12-30","saat":"","aciklama":"ALINAN PARA","no":"0051052","belge_no":""},{"id":"dek_1773254786128_311","tur":"borc","tutar":65,"tarih":"2025-12-30","saat":"","aciklama":"3/8 SARI TE 1 ADET","no":"0051053","belge_no":""},{"id":"dek_1773254786128_312","tur":"borc","tutar":23,"tarih":"2025-12-30","saat":"","aciklama":"3/8 SARI NİPEL 1 ADET","no":"0051054","belge_no":""},{"id":"dek_1773254786128_313","tur":"borc","tutar":270,"tarih":"2025-12-30","saat":"","aciklama":"3/8 MİNİ KÜRESEL VANA 2 ADET","no":"0051055","belge_no":""},{"id":"dek_1773254786128_314","tur":"borc","tutar":30,"tarih":"2025-12-30","saat":"","aciklama":"20*1/2 DİŞİ TE 1 ADET","no":"0051056","belge_no":""},{"id":"dek_1773254786128_315","tur":"tahsilat","tutar":388,"tarih":"2026-01-14","saat":"","aciklama":"ALINAN PARA","no":"0051345","belge_no":""},{"id":"dek_1773254786128_316","tur":"borc","tutar":100,"tarih":"2026-01-20","saat":"","aciklama":"BATARYA KARTUŞU 1 ADET","no":"0051475","belge_no":""},{"id":"dek_1773254786128_317","tur":"borc","tutar":150,"tarih":"2026-01-20","saat":"","aciklama":"BERBER BATARYASI HORTUMU 1 ADET","no":"0051477","belge_no":""},{"id":"dek_1773254786128_318","tur":"borc","tutar":1000,"tarih":"2026-02-26","saat":"","aciklama":"İLHAN LAVABO BATARYASI 1 ADET","no":"0052312","belge_no":""},{"id":"dek_1773254786128_319","tur":"borc","tutar":750,"tarih":"2026-02-26","saat":"","aciklama":"JAPAR GÖMME FLATÖRÜ 1 ADET","no":"0052313","belge_no":""}]